shops/__init__.py
shops/osm.py
shops-0.0.4.dist-info/METADATA
shops-0.0.4.dist-info/WHEEL
shops-0.0.4.dist-info/top_level.txt
shops-0.0.4.dist-info/RECORD
