Metadata-Version: 2.1
Name: shops
Version: 0.0.4
Summary: Provides data about shops in a given location, based on OpenStreetMap data.
Home-page: https://codeberg.org/matkoniecz/shop_listing
Author: Mateusz Konieczny
Author-email: matkoniecz@tutanota.com
License: UNKNOWN
Platform: UNKNOWN
Requires-Dist: osm-bot-abstraction-layer
Requires-Dist: osmium
